MANIFEST.in
README.md
setup.py
trex/__init__.py
trex/conf/__init__.py
trex/conf/junk_conf.py
trex/utils/__init__.py
trex/utils/common/__init__.py
trex/utils/common/cache_util.py
trex/utils/common/common_util.py
trex/utils/common/crm_util.py
trex/utils/common/date_util.py
trex/utils/common/float_util.py
trex/utils/common/pagination_uti;.py
trex/utils/common/phone_util.py
trex/utils/common/user_util.py
trexjunk.egg-info/PKG-INFO
trexjunk.egg-info/SOURCES.txt
trexjunk.egg-info/dependency_links.txt
trexjunk.egg-info/requires.txt
trexjunk.egg-info/top_level.txt