Metadata-Version: 1.1
Name: trexjunk
Version: 0.3.2
Summary: TRex junk library package
Home-page: UNKNOWN
Author: Jack Lok
Author-email: sglok77@gmail.com
License: UNKNOWN
Platform: UNKNOWN
Classifier: Programming Language :: Python :: 3
Classifier: License :: OSI Approved :: MIT License
Classifier: Operating System :: OS Independent
